dicekit/__init__.py
dicekit-0.1.1.dist-info/licenses/LICENSE
dicekit-0.1.1.dist-info/METADATA
dicekit-0.1.1.dist-info/WHEEL
dicekit-0.1.1.dist-info/top_level.txt
dicekit-0.1.1.dist-info/RECORD
