Metadata-Version: 2.4
Name: dicekit
Version: 0.1.1
Summary: Domain specific environment for dice
Author: Vincent D. Warmerdam
License: MIT License
Project-URL: repository, https://github.com/koaning/mohtml
Project-URL: issue-tracker, https://github.com/koaning/mohtml/issues
Project-URL: documentation, https://koaning.github.io/mohtml/
Classifier: Programming Language :: Python :: 3
Classifier: Programming Language :: Python :: 3.10
Classifier: Programming Language :: Python :: 3.11
Classifier: Programming Language :: Python :: 3.12
Classifier: License :: OSI Approved :: MIT License
Classifier: Topic :: Scientific/Engineering
Classifier: Topic :: Scientific/Engineering :: Artificial Intelligence
Classifier: Topic :: Software Development :: Libraries :: Python Modules
License-File: LICENSE
Requires-Dist: altair
Requires-Dist: pandas
Requires-Dist: marimo
Dynamic: license-file
